odoo10_addon_l10n_es_aeat_mod216-10.0.1.0.1.99.dev9-py3.8-nspkg.pth
odoo/addons/l10n_es_aeat_mod216/README.rst
odoo/addons/l10n_es_aeat_mod216/__init__.py
odoo/addons/l10n_es_aeat_mod216/__manifest__.py
odoo/addons/l10n_es_aeat_mod216/data/aeat_export_mod216_data.xml
odoo/addons/l10n_es_aeat_mod216/data/tax_code_map_mod216_data.xml
odoo/addons/l10n_es_aeat_mod216/docs/DR-216e16_v1.06.pdf
odoo/addons/l10n_es_aeat_mod216/i18n/bg.po
odoo/addons/l10n_es_aeat_mod216/i18n/ca.po
odoo/addons/l10n_es_aeat_mod216/i18n/cs.po
odoo/addons/l10n_es_aeat_mod216/i18n/de.po
odoo/addons/l10n_es_aeat_mod216/i18n/es.po
odoo/addons/l10n_es_aeat_mod216/i18n/es_CO.po
odoo/addons/l10n_es_aeat_mod216/i18n/es_CR.po
odoo/addons/l10n_es_aeat_mod216/i18n/es_ES.po
odoo/addons/l10n_es_aeat_mod216/i18n/eu.po
odoo/addons/l10n_es_aeat_mod216/i18n/fr.po
odoo/addons/l10n_es_aeat_mod216/i18n/gl.po
odoo/addons/l10n_es_aeat_mod216/i18n/hr.po
odoo/addons/l10n_es_aeat_mod216/i18n/l10n_es_aeat_mod216.pot
odoo/addons/l10n_es_aeat_mod216/i18n/nl.po
odoo/addons/l10n_es_aeat_mod216/i18n/pl.po
odoo/addons/l10n_es_aeat_mod216/i18n/pt.po
odoo/addons/l10n_es_aeat_mod216/i18n/pt_BR.po
odoo/addons/l10n_es_aeat_mod216/i18n/ru.po
odoo/addons/l10n_es_aeat_mod216/i18n/sl.po
odoo/addons/l10n_es_aeat_mod216/i18n/sv.po
odoo/addons/l10n_es_aeat_mod216/i18n/tr.po
odoo/addons/l10n_es_aeat_mod216/i18n/vi.po
odoo/addons/l10n_es_aeat_mod216/models/__init__.py
odoo/addons/l10n_es_aeat_mod216/models/mod111.py
odoo/addons/l10n_es_aeat_mod216/models/mod216.py
odoo/addons/l10n_es_aeat_mod216/models/res_partner.py
odoo/addons/l10n_es_aeat_mod216/readme/CONFIGURE.rst
odoo/addons/l10n_es_aeat_mod216/readme/CONTRIBUTORS.rst
odoo/addons/l10n_es_aeat_mod216/readme/DESCRIPTION.rst
odoo/addons/l10n_es_aeat_mod216/readme/USAGE.rst
odoo/addons/l10n_es_aeat_mod216/security/ir.model.access.csv
odoo/addons/l10n_es_aeat_mod216/static/description/icon.png
odoo/addons/l10n_es_aeat_mod216/static/description/icon_source.svg
odoo10_addon_l10n_es_aeat_mod216-10.0.1.0.1.99.dev9.dist-info/METADATA
odoo10_addon_l10n_es_aeat_mod216-10.0.1.0.1.99.dev9.dist-info/WHEEL
odoo10_addon_l10n_es_aeat_mod216-10.0.1.0.1.99.dev9.dist-info/namespace_packages.txt
odoo10_addon_l10n_es_aeat_mod216-10.0.1.0.1.99.dev9.dist-info/top_level.txt
odoo10_addon_l10n_es_aeat_mod216-10.0.1.0.1.99.dev9.dist-info/RECORD
