Metadata-Version: 2.1
Name: odoo10-addon-l10n-es-aeat-mod216
Version: 10.0.1.0.1.99.dev9
Summary: AEAT modelo 216
Home-page: https://github.com/OCA/l10n-spain
Author: AvanzOSC,Tecnativa,Odoo Community Association (OCA)
Author-email: support@odoo-community.org
License: AGPL-3
Platform: UNKNOWN
Classifier: Programming Language :: Python
Classifier: Framework :: Odoo
Classifier: Framework :: Odoo :: 10.0
Classifier: License :: OSI Approved :: GNU Affero General Public License v3
Classifier: Development Status :: 6 - Mature
Requires-Python: ~=2.7
Requires-Dist: odoo10-addon-l10n-es-aeat-mod111
Requires-Dist: odoo <10.1dev,>=10.0
